transformers_agent_ui/__init__.py
transformers_agent_ui/py.typed
transformers_agent_ui/assets/__init__.py
transformers_agent_ui/assets/boat-in-water.png
transformers_agent_ui/assets/capybara.png
transformers_agent_ui/domain/__init__.py
transformers_agent_ui/domain/agent.py
transformers_agent_ui/domain/config.py
transformers_agent_ui/domain/custom_run.py
transformers_agent_ui/domain/examples.py
transformers_agent_ui/domain/run.py
transformers_agent_ui/domain/store.py
transformers_agent_ui/domain/token.py
transformers_agent_ui/ui/__init__.py
transformers_agent_ui/ui/components.py
transformers_agent_ui/ui/config.py
transformers_agent_ui/ui/token_manager.py
transformers_agent_ui/ui/transformers_agent_ui.py
transformers_agent_ui-0.4.1.dist-info/METADATA
transformers_agent_ui-0.4.1.dist-info/WHEEL
transformers_agent_ui-0.4.1.dist-info/top_level.txt
transformers_agent_ui-0.4.1.dist-info/RECORD
