Metadata-Version: 2.1
Name: transformers-agent-ui
Version: 0.4.1
Summary: This package makes it super simple to do exploratory data analysis and develop high-quality Panel data apps ...
Author: awesome-panel
Project-URL: repository, https://github.com/awesome-panel/transformers-agent-ui
Keywords: python,huggingface,transformers,deeplearning,ai,agent,holoviz,panel
Classifier: License :: OSI Approved :: MIT License
Classifier: Development Status :: 3 - Alpha
Classifier: Programming Language :: Python :: 3
Classifier: Programming Language :: Python :: 3.7
Classifier: Programming Language :: Python :: 3.8
Classifier: Programming Language :: Python :: 3.9
Classifier: Programming Language :: Python :: 3.10
Classifier: Operating System :: OS Independent
Classifier: Intended Audience :: Developers
Classifier: Intended Audience :: Education
Classifier: Intended Audience :: Financial and Insurance Industry
Classifier: Intended Audience :: Healthcare Industry
Classifier: Intended Audience :: Information Technology
Classifier: Intended Audience :: Legal Industry
Classifier: Intended Audience :: Other Audience
Classifier: Intended Audience :: Science/Research
Classifier: Natural Language :: English
Classifier: Topic :: Office/Business :: Financial
Classifier: Topic :: Office/Business
Classifier: Topic :: Scientific/Engineering :: Information Analysis
Classifier: Topic :: Scientific/Engineering :: Visualization
Classifier: Topic :: Scientific/Engineering
Classifier: Topic :: Software Development :: Libraries
Requires-Python: >=3.7
Requires-Dist: openai
Requires-Dist: panel (>=1.0.0rc8)
Requires-Dist: param (<2.0)
Requires-Dist: torchaudio
Requires-Dist: transformers[agents]
Provides-Extra: dev
Requires-Dist: awesome-panel-cli[dev] ; extra == 'dev'
Requires-Dist: types-Pillow ; extra == 'dev'
Provides-Extra: examples
Requires-Dist: awesome-panel-cli ; extra == 'examples'
Requires-Dist: notebook ; extra == 'examples'
